{"cn_community_contrib_index.md":"BRXwRrnW","cn_community_qa_index.md":"DihOzWy5","cn_guide_config_index.md":"DQuTk6so","cn_guide_core-commands_index.md":"B7Nck7Mv","cn_guide_custom-commands_index.md":"DTuUJDlV","cn_guide_hook_index.md":"Cpyj3NFa","cn_guide_index.md":"DTkzpN0l","cn_guide_plugin_index.md":"xkvSxvm2","cn_guide_quickstart_index.md":"D1TUSuhF","cn_index.md":"Brof5LI0","cn_usage_distribution_index.md":"DGXAdvxZ","cn_usage_index.md":"JDIXMdVV","cn_usage_integration_index.md":"CQoUq3w8","cn_usage_plugin_index.md":"9yxThx6l","cn_usage_solution_index.md":"QmWRm9kI","community_contrib_index.md":"DYUnvZnu","community_qa_index.md":"B2BW5rd1","guide_config_index.md":"ApE8hydo","guide_core-commands_index.md":"CWG_Pnnp","guide_custom-commands_index.md":"DeA2G8kO","guide_hook_index.md":"C2_9hdMr","guide_index.md":"CFbLCaih","guide_plugin_index.md":"DKiIYNGF","guide_quickstart_index.md":"CsKQn5RN","index.md":"nU9sw6Yl","usage_distribution_index.md":"BV9aF3Os","usage_index.md":"KngQkgGS","usage_integration_index.md":"CfPEYuSc","usage_plugin_index.md":"C_CgDt6Z","usage_solution_index.md":"C6Y1J7pf"}
